{"diagram": {"data": {"id": "diagram-0", "name": "DIPAM for Textual anlysis", "type": "diagram"}}, "edges": [{"data": {"id": "e-0001", "name": "e-0001", "source": "d-0001", "target": "t-0002", "type": "edge", "value": ""}}, {"data": {"id": "e-0002", "name": "e-0002", "source": "d-0001", "target": "t-0003", "type": "edge", "value": ""}}, {"data": {"id": "e-0003", "name": "e-0003", "source": "t-0003", "target": "t-0002", "type": "edge", "value": ""}}, {"data": {"id": "e-0004", "name": "e-0004", "source": "d-0001", "target": "t-0001", "type": "edge", "value": ""}}, {"data": {"id": "e-0005", "name": "e-0005", "source": "t-0001", "target": "t-0002", "type": "edge", "value": ""}}], "nodes": [{"data": {"graph": {"position": {"x": 675.1522879902124, "y": -193.18449747340776}}, "id": "d-0001", "name": "AH Data", "param": {"p-file": {"0": {}}}, "type": "data", "value": "d-gen-text"}}, {"data": {"graph": {"position": {"x": 1114.643999597125, "y": -5.607432980593462}}, "id": "t-0002", "name": "Save Results", "param": {}, "type": "tool", "value": "t-save-files"}}, {"data": {"graph": {"position": {"x": 690.5550495578699, "y": 127.91995791853543}}, "id": "t-0003", "name": "LDA Topic Modelling", "param": {"p-numwords": "10", "p-topic": "2"}, "type": "tool", "value": "t-topic-lda"}}, {"data": {"graph": {"position": {"x": 897.2559841902812, "y": -10.326982485417172}}, "id": "t-0001", "name": "Filter Dates", "param": {"p-filteropt": ["dates"], "p-filterregex": "\\d{4}"}, "type": "tool", "value": "t-filter-text"}}]}